<annotation>
	<folder>images</folder>
	<filename>000071.jpg</filename>
	<path>F:\zidongbiaozhu\detectAuto-main\images\000071.jpg</path>
	<source>
		<database>Unknown</database>
	</source>
	<size>
		<width>832</width>
		<height>832</height>
		<depth>3</depth>
	</size>
	<segmented>0</segmented>
	<object>
		<name>no-hat</name>
		<pose>Unspecified</pose>
		<truncated>0</truncated>
		<difficult>0</difficult>
		<bndbox>
			<xmin>332</xmin>
			<ymin>112</ymin>
			<xmax>384</xmax>
			<ymax>150</ymax>
		</bndbox>
	</object>
</annotation>
